odoo/addons/product_allergen/README.rst
odoo/addons/product_allergen/__init__.py
odoo/addons/product_allergen/__manifest__.py
odoo/addons/product_allergen/data/allergen_data.xml
odoo/addons/product_allergen/i18n/es.po
odoo/addons/product_allergen/i18n/product_allergen.pot
odoo/addons/product_allergen/models/__init__.py
odoo/addons/product_allergen/models/allergen_allergen.py
odoo/addons/product_allergen/models/product_product.py
odoo/addons/product_allergen/models/product_template.py
odoo/addons/product_allergen/models/res_config_settings.py
odoo/addons/product_allergen/readme/CONFIGURE.md
odoo/addons/product_allergen/readme/DESCRIPTION.md
odoo/addons/product_allergen/readme/ROADMAP.md
odoo/addons/product_allergen/readme/USAGE.md
odoo/addons/product_allergen/report/product_product_templates.xml
odoo/addons/product_allergen/security/ir.model.access.csv
odoo/addons/product_allergen/static/description/icon.png
odoo/addons/product_allergen/static/description/index.html
odoo/addons/product_allergen/static/img/allergen_icons/Celery.png
odoo/addons/product_allergen/static/img/allergen_icons/Celery.svg
odoo/addons/product_allergen/static/img/allergen_icons/Crustaceans.png
odoo/addons/product_allergen/static/img/allergen_icons/Crustaceans.svg
odoo/addons/product_allergen/static/img/allergen_icons/Fish.png
odoo/addons/product_allergen/static/img/allergen_icons/Fish.svg
odoo/addons/product_allergen/static/img/allergen_icons/Gluten.png
odoo/addons/product_allergen/static/img/allergen_icons/Gluten.svg
odoo/addons/product_allergen/static/img/allergen_icons/Lupin.png
odoo/addons/product_allergen/static/img/allergen_icons/Lupin.svg
odoo/addons/product_allergen/static/img/allergen_icons/Molluscs.png
odoo/addons/product_allergen/static/img/allergen_icons/Molluscs.svg
odoo/addons/product_allergen/static/img/allergen_icons/Mustard.png
odoo/addons/product_allergen/static/img/allergen_icons/Mustard.svg
odoo/addons/product_allergen/static/img/allergen_icons/Peanuts.png
odoo_addon_product_allergen-18.0.1.0.0.2.dist-info/METADATA
odoo_addon_product_allergen-18.0.1.0.0.2.dist-info/WHEEL
odoo_addon_product_allergen-18.0.1.0.0.2.dist-info/top_level.txt
odoo_addon_product_allergen-18.0.1.0.0.2.dist-info/RECORD
